{
  "type": "FeatureCollection",
  "features": [{
      "type": "Feature",
      "geometry": {
        "type": "Point",
        "coordinates": [48.654403, 8.330409]
      },
      "properties": {
        "name": "Forbach Talsperre"
      }
    }, {
      "type": "Feature",
      "geometry": {
        "type": "Point",
        "coordinates": [48.66903,8.35286]
      },
      "properties": {
        "name": "Forbach Kraftwerk"
      }
    }, {
      "type": "Feature",
      "geometry": {
        "type": "Point",
        "coordinates": [48.668501, 8.353368]
      },
      "properties": {
        "name": "Something other"
      }
    }]
}
    
    


