{
  "type": "FeatureCollection",
  "features": [{
      "type": "Feature",
      "geometry": {
        "type": "Point",
        "coordinates": [8.330409,48.654403]
      },
      "properties": {
        "name": "Forbach Talsperre",
        "marker-size": "small",
        "marker-color": "#f0f0f0"
      }
    }, {
      "type": "Feature",
      "geometry": {
        "type": "Point",
        "coordinates": [8.35286,48.66903]
      },
      "properties": {
        "name": "Forbach Kraftwerk",
        "marker-size": "small"
      }
    }]
}
    
    
    
    


