{
  "type": "FeatureCollection",
  "features": [{
      "type": "Feature",
      "geometry": {
        "type": "Point",
        "coordinates": [8.330409, 48.654403]
      },
      "properties": {
        "name": "Forbach Talsperre"
      }
    }, {
      "type": "Feature",
      "geometry": {
        "type": "Point",
        "coordinates": [8.353368, 48.668501]
      },
      "properties": {
        "name": "Forbach Kraftwerk"
      }
    }, {
      "type": "Feature",
      "geometry": {
        "type": "Point",
        "coordinates": [8.353368, 48.668501]
      },
      "properties": {
        "name": "Forbach Kraftwerk Klon"
      }
    }, {
      "type": "Feature",
      "geometry": {
        "type": "Point",
        "coordinates": [-81.299554906610865, 32.354080966941915]
      },
      "properties": {
        "name": "Something other"
      }
    }]
}
    
    


