{
  "type": "FeatureCollection",
  "features": [{
      "type": "Feature",
      "geometry": {
        "type": "Point",
        "coordinates": [8.330409,48.654403]
      },
      "properties": {
        "name": "Forbach Talsperre"
      }
    }, {
      "type": "Feature",
      "geometry": {
        "type": "Point",
        "coordinates": [8.35286,48.66903]
      },
      "properties": {
        "name": "Forbach Kraftwerk"
      }
    }, {
      "type": "Feature",
      "geometry": {
        "type": "Point",
        "coordinates": [9.233626644885119,48.84941688864243]
      },
      "properties": {
        "name": "Stuttgart"
      }
    }]
}
    
    
    
    


