{
  "type": "FeatureCollection",
  "features": [{
      "type": "Feature",
      "geometry": {
        "type": "Point",
        "coordinates": [48.654403, 8.330409]
      },
      "properties": {
        "name": "Forbach Talsperre"
      }
    }, {
      "type": "Feature",
      "geometry": {
        "type": "Point",
        "coordinates": [48.668501, 8.353368]
      },
      "properties": {
        "name": "Forbach Kraftwerk"
      }
    }, {
      "type": "Feature",
      "geometry": {
        "type": "Point",
        "coordinates": [-81.299554906610865, 32.354080966941915]
      },
      "properties": {
        "name": "Something other"
      }
    }]
}
    
    


