{
  "type": "FeatureCollection",
  "features": [{
      "type": "Feature",
      "geometry": {
        "type": "Point",
        "coordinates": [48.654403, 8.330409]
      },
      "properties": {
        "name": "Forbach Talsperre"
      }
    }, {
      "type": "Feature",
      "geometry": {
        "type": "Point",
        "coordinates": [48.66903, 8.35286]
      },
      "properties": {
        "name": "Forbach Kraftwerk"
      }
    }, {
      "type": "Feature",
      "geometry": {
        "type": "Point",
        "coordinates": [52.520325, 13.380344]
      },
      "properties": {
        "name": "Stuttgart"
      }
    }, {
      "type": "Feature",
      "geometry": {
        "type": "Point",
        "coordinates": [9.233626644885119,48.84941688864243]
      },
      "properties": {
        "name": "Something other"
      }
    }]
}
    
    
    
    


